{"cod":"200","message":0,"cnt":40,"list":[{"dt":1736434800,"main":{"temp":10.94,"feels_like":9.92,"temp_min":8.71,"temp_max":10.94,"pressure":999,"sea_level":999,"grnd_level":964,"humidity":70,"temp_kf":2.23},"weather":[{"id":802,"main":"Clouds","description":"scattered clouds","icon":"03d"}],"clouds":{"all":27},"wind":{"speed":5.38,"deg":185,"gust":13.28},"visibility":10000,"pop":0,"sys":{"pod":"d"},"dt_txt":"2025-01-09 15:00:00"},{"dt":1736445600,"main":{"temp":9.73,"feels_like":6.26,"temp_min":8.56,"temp_max":9.73,"pressure":998,"sea_level":998,"grnd_level":963,"humidity":77,"temp_kf":1.17},"weather":[{"id":500,"main":"Rain","description":"light rain","icon":"10n"}],"clouds":{"all":59},"wind":{"speed":8.25,"deg":205,"gust":16.53},"visibility":4901,"pop":1,"rain":{"3h":1.7},"sys":{"pod":"n"},"dt_txt":"2025-01-09 18:00:00"},{"dt":1736456400,"main":{"temp":1.78,"feels_like":-4.23,"temp_min":1.78,"temp_max":1.78,"pressure":1003,"sea_level":1003,"grnd_level":968,"humidity":75,"temp_kf":0},"weather":[{"id":601,"main":"Snow","description":"snow","icon":"13n"}],"clouds":{"all":100},"wind":{"speed":8.63,"deg":287,"gust":15.7},"visibility":10000,"pop":1,"snow":{"3h":2.18},"sys":{"pod":"n"},"dt_txt":"2025-01-09 21:00:00"},{"dt":1736467200,"main":{"temp":1.81,"feels_like":-4.05,"temp_min":1.81,"temp_max":1.81,"pressure":1010,"sea_level":1010,"grnd_level":974,"humidity":73,"temp_kf":0},"weather":[{"id":804,"main":"Clouds","description":"overcast clouds","icon":"04n"}],"clouds":{"all":88},"wind":{"speed":8.2,"deg":271,"gust":16.01},"visibility":10000,"pop":0.8,"sys":{"pod":"n"},"dt_txt":"2025-01-10 00:00:00"},{"dt":1736478000,"main":{"temp":1.77,"feels_like":-4.35,"temp_min":1.77,"temp_max":1.77,"pressure":1012,"sea_level":1012,"grnd_level":977,"humidity":71,"temp_kf":0},"weather":[{"id":803,"main":"Clouds","description":"broken clouds","icon":"04n"}],"clouds":{"all":72},"wind":{"speed":8.93,"deg":273,"gust":15.71},"visibility":10000,"pop":0,"sys":{"pod":"n"},"dt_txt":"2025-01-10 03:00:00"},{"dt":1736488800,"main":{"temp":0.51,"feels_like":-5.31,"temp_min":0.51,"temp_max":0.51,"pressure":1015,"sea_level":1015,"grnd_level":979,"humidity":73,"temp_kf":0},"weather":[{"id":804,"main":"Clouds","description":"overcast clouds","icon":"04n"}],"clouds":{"all":85},"wind":{"speed":7.12,"deg":270,"gust":13.16},"visibility":10000,"pop":0,"sys":{"pod":"n"},"dt_txt":"2025-01-10 06:00:00"},{"dt":1736499600,"main":{"temp":1.24,"feels_like":-4.21,"temp_min":1.24,"temp_max":1.24,"pressure":1017,"sea_level":1017,"grnd_level":981,"humidity":66,"temp_kf":0},"weather":[{"id":803,"main":"Clouds","description":"broken clouds","icon":"04d"}],"clouds":{"all":70},"wind":{"speed":6.75,"deg":262,"gust":11.84},"visibility":10000,"pop":0,"sys":{"pod":"d"},"dt_txt":"2025-01-10 09:00:00"},{"dt":1736510400,"main":{"temp":2.36,"feels_like":-3.19,"temp_min":2.36,"temp_max":2.36,"pressure":1016,"sea_level":1016,"grnd_level":980,"humidity":61,"temp_kf":0},"weather":[{"id":803,"main":"Clouds","description":"broken clouds","icon":"04d"}],"clouds":{"all":53},"wind":{"speed":7.8,"deg":261,"gust":12.27},"visibility":10000,"pop":0,"sys":{"pod":"d"},"dt_txt":"2025-01-10 12:00:00"},{"dt":1736521200,"main":{"temp":1.53,"feels_like":-3.98,"temp_min":1.53,"temp_max":1.53,"pressure":1017,"sea_level":1017,"grnd_level":981,"humidity":69,"temp_kf":0},"weather":[{"id":803,"main":"Clouds","description":"broken clouds","icon":"04d"}],"clouds":{"all":68},"wind":{"speed":7.09,"deg":265,"gust":12.43},"visibility":10000,"pop":0,"sys":{"pod":"d"},"dt_txt":"2025-01-10 15:00:00"},{"dt":1736532000,"main":{"temp":0.57,"feels_like":-5.32,"temp_min":0.57,"temp_max":0.57,"pressure":1017,"sea_level":1017,"grnd_level":981,"humidity":68,"temp_kf":0},"weather":[{"id":802,"main":"Clouds","description":"scattered clouds","icon":"03n"}],"clouds":{"all":42},"wind":{"speed":7.33,"deg":259,"gust":13.35},"visibility":10000,"pop":0,"sys":{"pod":"n"},"dt_txt":"2025-01-10 18:00:00"},{"dt":1736542800,"main":{"temp":0.18,"feels_like":-5.82,"temp_min":0.18,"temp_max":0.18,"pressure":1017,"sea_level":1017,"grnd_level":981,"humidity":73,"temp_kf":0},"weather":[{"id":802,"main":"Clouds","description":"scattered clouds","icon":"03n"}],"clouds":{"all":46},"wind":{"speed":7.33,"deg":259,"gust":13.16},"visibility":10000,"pop":0,"sys":{"pod":"n"},"dt_txt":"2025-01-10 21:00:00"},{"dt":1736553600,"main":{"temp":-0.46,"feels_like":-5.99,"temp_min":-0.46,"temp_max":-0.46,"pressure":1018,"sea_level":1018,"grnd_level":982,"humidity":79,"temp_kf":0},"weather":[{"id":802,"main":"Clouds","description":"scattered clouds","icon":"03n"}],"clouds":{"all":45},"wind":{"speed":5.91,"deg":260,"gust":10.97},"visibility":10000,"pop":0,"sys":{"pod":"n"},"dt_txt":"2025-01-11 00:00:00"},{"dt":1736564400,"main":{"temp":-0.57,"feels_like":-5.81,"temp_min":-0.57,"temp_max":-0.57,"pressure":1018,"sea_level":1018,"grnd_level":982,"humidity":79,"temp_kf":0},"weather":[{"id":803,"main":"Clouds","description":"broken clouds","icon":"04n"}],"clouds":{"all":74},"wind":{"speed":5.32,"deg":261,"gust":10.39},"visibility":10000,"pop":0,"sys":{"pod":"n"},"dt_txt":"2025-01-11 03:00:00"},{"dt":1736575200,"main":{"temp":-0.73,"feels_like":-5.68,"temp_min":-0.73,"temp_max":-0.73,"pressure":1019,"sea_level":1019,"grnd_level":983,"humidity":79,"temp_kf":0},"weather":[{"id":803,"main":"Clouds","description":"broken clouds","icon":"04n"}],"clouds":{"all":74},"wind":{"speed":4.76,"deg":266,"gust":9.45},"visibility":10000,"pop":0,"sys":{"pod":"n"},"dt_txt":"2025-01-11 06:00:00"},{"dt":1736586000,"main":{"temp":-0.18,"feels_like":-4.73,"temp_min":-0.18,"temp_max":-0.18,"pressure":1020,"sea_level":1020,"grnd_level":984,"humidity":80,"temp_kf":0},"weather":[{"id":600,"main":"Snow","description":"light snow","icon":"13d"}],"clouds":{"all":95},"wind":{"speed":4.34,"deg":283,"gust":9.04},"visibility":10000,"pop":0.25,"snow":{"3h":0.23},"sys":{"pod":"d"},"dt_txt":"2025-01-11 09:00:00"},{"dt":1736596800,"main":{"temp":0.98,"feels_like":-4.78,"temp_min":0.98,"temp_max":0.98,"pressure":1020,"sea_level":1020,"grnd_level":984,"humidity":58,"temp_kf":0},"weather":[{"id":804,"main":"Clouds","description":"overcast clouds","icon":"04d"}],"clouds":{"all":93},"wind":{"speed":7.3,"deg":301,"gust":11.53},"visibility":10000,"pop":0,"sys":{"pod":"d"},"dt_txt":"2025-01-11 12:00:00"},{"dt":1736607600,"main":{"temp":-0.32,"feels_like":-6.39,"temp_min":-0.32,"temp_max":-0.32,"pressure":1021,"sea_level":1021,"grnd_level":985,"humidity":63,"temp_kf":0},"weather":[{"id":803,"main":"Clouds","description":"broken clouds","icon":"04d"}],"clouds":{"all":70},"wind":{"speed":7.14,"deg":289,"gust":13.66},"visibility":10000,"pop":0,"sys":{"pod":"d"},"dt_txt":"2025-01-11 15:00:00"},{"dt":1736618400,"main":{"temp":-0.17,"feels_like":-6.57,"temp_min":-0.17,"temp_max":-0.17,"pressure":1022,"sea_level":1022,"grnd_level":986,"humidity":66,"temp_kf":0},"weather":[{"id":803,"main":"Clouds","description":"broken clouds","icon":"04n"}],"clouds":{"all":83},"wind":{"speed":8.07,"deg":293,"gust":14.68},"visibility":10000,"pop":0,"sys":{"pod":"n"},"dt_txt":"2025-01-11 18:00:00"},{"dt":1736629200,"main":{"temp":0.07,"feels_like":-6.32,"temp_min":0.07,"temp_max":0.07,"pressure":1023,"sea_level":1023,"grnd_level":987,"humidity":69,"temp_kf":0},"weather":[{"id":804,"main":"Clouds","description":"overcast clouds","icon":"04n"}],"clouds":{"all":100},"wind":{"speed":8.23,"deg":293,"gust":14.54},"visibility":10000,"pop":0,"sys":{"pod":"n"},"dt_txt":"2025-01-11 21:00:00"},{"dt":1736640000,"main":{"temp":-0.49,"feels_like":-6.93,"temp_min":-0.49,"temp_max":-0.49,"pressure":1025,"sea_level":1025,"grnd_level":988,"humidity":79,"temp_kf":0},"weather":[{"id":600,"main":"Snow","description":"light snow","icon":"13n"}],"clouds":{"all":100},"wind":{"speed":7.91,"deg":297,"gust":14.03},"visibility":8881,"pop":0.21,"snow":{"3h":0.16},"sys":{"pod":"n"},"dt_txt":"2025-01-12 00:00:00"},{"dt":1736650800,"main":{"temp":-0.99,"feels_like":-6.88,"temp_min":-0.99,"temp_max":-0.99,"pressure":1027,"sea_level":1027,"grnd_level":990,"humidity":89,"temp_kf":0},"weather":[{"id":600,"main":"Snow","description":"light snow","icon":"13n"}],"clouds":{"all":100},"wind":{"speed":6.35,"deg":300,"gust":11.69},"visibility":5129,"pop":0.9,"snow":{"3h":0.56},"sys":{"pod":"n"},"dt_txt":"2025-01-12 03:00:00"},{"dt":1736661600,"main":{"temp":-1.08,"feels_like":-6.94,"temp_min":-1.08,"temp_max":-1.08,"pressure":1029,"sea_level":1029,"grnd_level":992,"humidity":84,"temp_kf":0},"weather":[{"id":600,"main":"Snow","description":"light snow","icon":"13n"}],"clouds":{"all":100},"wind":{"speed":6.24,"deg":299,"gust":11.09},"visibility":10000,"pop":0.77,"snow":{"3h":0.27},"sys":{"pod":"n"},"dt_txt":"2025-01-12 06:00:00"},{"dt":1736672400,"main":{"temp":-0.68,"feels_like":-6.19,"temp_min":-0.68,"temp_max":-0.68,"pressure":1031,"sea_level":1031,"grnd_level":995,"humidity":78,"temp_kf":0},"weather":[{"id":600,"main":"Snow","description":"light snow","icon":"13d"}],"clouds":{"all":100},"wind":{"speed":5.77,"deg":307,"gust":9.82},"visibility":10000,"pop":0.31,"snow":{"3h":0.15},"sys":{"pod":"d"},"dt_txt":"2025-01-12 09:00:00"},{"dt":1736683200,"main":{"temp":0.27,"feels_like":-5.23,"temp_min":0.27,"temp_max":0.27,"pressure":1033,"sea_level":1033,"grnd_level":996,"humidity":72,"temp_kf":0},"weather":[{"id":600,"main":"Snow","description":"light snow","icon":"13d"}],"clouds":{"all":100},"wind":{"speed":6.26,"deg":321,"gust":9.08},"visibility":10000,"pop":0.34,"snow":{"3h":0.13},"sys":{"pod":"d"},"dt_txt":"2025-01-12 12:00:00"},{"dt":1736694000,"main":{"temp":-0.99,"feels_like":-5.94,"temp_min":-0.99,"temp_max":-0.99,"pressure":1035,"sea_level":1035,"grnd_level":998,"humidity":74,"temp_kf":0},"weather":[{"id":803,"main":"Clouds","description":"broken clouds","icon":"04d"}],"clouds":{"all":77},"wind":{"speed":4.65,"deg":315,"gust":8.8},"visibility":10000,"pop":0,"sys":{"pod":"d"},"dt_txt":"2025-01-12 15:00:00"},{"dt":1736704800,"main":{"temp":-2.26,"feels_like":-6.87,"temp_min":-2.26,"temp_max":-2.26,"pressure":1038,"sea_level":1038,"grnd_level":1000,"humidity":80,"temp_kf":0},"weather":[{"id":802,"main":"Clouds","description":"scattered clouds","icon":"03n"}],"clouds":{"all":41},"wind":{"speed":3.76,"deg":299,"gust":8.32},"visibility":10000,"pop":0,"sys":{"pod":"n"},"dt_txt":"2025-01-12 18:00:00"},{"dt":1736715600,"main":{"temp":-2.38,"feels_like":-6.64,"temp_min":-2.38,"temp_max":-2.38,"pressure":1039,"sea_level":1039,"grnd_level":1002,"humidity":81,"temp_kf":0},"weather":[{"id":803,"main":"Clouds","description":"broken clouds","icon":"04n"}],"clouds":{"all":64},"wind":{"speed":3.31,"deg":308,"gust":5.86},"visibility":10000,"pop":0,"sys":{"pod":"n"},"dt_txt":"2025-01-12 21:00:00"},{"dt":1736726400,"main":{"temp":-1.61,"feels_like":-5.39,"temp_min":-1.61,"temp_max":-1.61,"pressure":1040,"sea_level":1040,"grnd_level":1002,"humidity":79,"temp_kf":0},"weather":[{"id":803,"main":"Clouds","description":"broken clouds","icon":"04n"}],"clouds":{"all":84},"wind":{"speed":2.95,"deg":281,"gust":4.88},"visibility":10000,"pop":0,"sys":{"pod":"n"},"dt_txt":"2025-01-13 00:00:00"},{"dt":1736737200,"main":{"temp":-3.26,"feels_like":-7.04,"temp_min":-3.26,"temp_max":-3.26,"pressure":1041,"sea_level":1041,"grnd_level":1003,"humidity":87,"temp_kf":0},"weather":[{"id":801,"main":"Clouds","description":"few clouds","icon":"02n"}],"clouds":{"all":20},"wind":{"speed":2.64,"deg":282,"gust":5.6},"visibility":10000,"pop":0,"sys":{"pod":"n"},"dt_txt":"2025-01-13 03:00:00"},{"dt":1736748000,"main":{"temp":-3.61,"feels_like":-5.92,"temp_min":-3.61,"temp_max":-3.61,"pressure":1042,"sea_level":1042,"grnd_level":1004,"humidity":88,"temp_kf":0},"weather":[{"id":801,"main":"Clouds","description":"few clouds","icon":"02n"}],"clouds":{"all":13},"wind":{"speed":1.53,"deg":296,"gust":2.27},"visibility":10000,"pop":0,"sys":{"pod":"n"},"dt_txt":"2025-01-13 06:00:00"},{"dt":1736758800,"main":{"temp":-2.41,"feels_like":-4.43,"temp_min":-2.41,"temp_max":-2.41,"pressure":1042,"sea_level":1042,"grnd_level":1005,"humidity":81,"temp_kf":0},"weather":[{"id":801,"main":"Clouds","description":"few clouds","icon":"02d"}],"clouds":{"all":15},"wind":{"speed":1.46,"deg":279,"gust":2.03},"visibility":10000,"pop":0,"sys":{"pod":"d"},"dt_txt":"2025-01-13 09:00:00"},{"dt":1736769600,"main":{"temp":-0.26,"feels_like":-2.43,"temp_min":-0.26,"temp_max":-0.26,"pressure":1041,"sea_level":1041,"grnd_level":1004,"humidity":67,"temp_kf":0},"weather":[{"id":801,"main":"Clouds","description":"few clouds","icon":"02d"}],"clouds":{"all":12},"wind":{"speed":1.75,"deg":309,"gust":2.45},"visibility":10000,"pop":0,"sys":{"pod":"d"},"dt_txt":"2025-01-13 12:00:00"},{"dt":1736780400,"main":{"temp":-1.15,"feels_like":-1.15,"temp_min":-1.15,"temp_max":-1.15,"pressure":1040,"sea_level":1040,"grnd_level":1003,"humidity":70,"temp_kf":0},"weather":[{"id":800,"main":"Clear","description":"clear sky","icon":"01d"}],"clouds":{"all":6},"wind":{"speed":1.21,"deg":261,"gust":1.27},"visibility":10000,"pop":0,"sys":{"pod":"d"},"dt_txt":"2025-01-13 15:00:00"},{"dt":1736791200,"main":{"temp":-2.29,"feels_like":-4.77,"temp_min":-2.29,"temp_max":-2.29,"pressure":1040,"sea_level":1040,"grnd_level":1003,"humidity":74,"temp_kf":0},"weather":[{"id":801,"main":"Clouds","description":"few clouds","icon":"02n"}],"clouds":{"all":22},"wind":{"speed":1.75,"deg":216,"gust":1.79},"visibility":10000,"pop":0,"sys":{"pod":"n"},"dt_txt":"2025-01-13 18:00:00"},{"dt":1736802000,"main":{"temp":-2.81,"feels_like":-5.08,"temp_min":-2.81,"temp_max":-2.81,"pressure":1040,"sea_level":1040,"grnd_level":1002,"humidity":76,"temp_kf":0},"weather":[{"id":802,"main":"Clouds","description":"scattered clouds","icon":"03n"}],"clouds":{"all":42},"wind":{"speed":1.57,"deg":211,"gust":1.67},"visibility":10000,"pop":0,"sys":{"pod":"n"},"dt_txt":"2025-01-13 21:00:00"},{"dt":1736812800,"main":{"temp":-3.2,"feels_like":-6.08,"temp_min":-3.2,"temp_max":-3.2,"pressure":1039,"sea_level":1039,"grnd_level":1001,"humidity":76,"temp_kf":0},"weather":[{"id":802,"main":"Clouds","description":"scattered clouds","icon":"03n"}],"clouds":{"all":49},"wind":{"speed":1.93,"deg":202,"gust":2.52},"visibility":10000,"pop":0,"sys":{"pod":"n"},"dt_txt":"2025-01-14 00:00:00"},{"dt":1736823600,"main":{"temp":-3.38,"feels_like":-6.56,"temp_min":-3.38,"temp_max":-3.38,"pressure":1037,"sea_level":1037,"grnd_level":1000,"humidity":75,"temp_kf":0},"weather":[{"id":802,"main":"Clouds","description":"scattered clouds","icon":"03n"}],"clouds":{"all":32},"wind":{"speed":2.12,"deg":202,"gust":2.74},"visibility":10000,"pop":0,"sys":{"pod":"n"},"dt_txt":"2025-01-14 03:00:00"},{"dt":1736834400,"main":{"temp":-3.46,"feels_like":-7.05,"temp_min":-3.46,"temp_max":-3.46,"pressure":1036,"sea_level":1036,"grnd_level":999,"humidity":71,"temp_kf":0},"weather":[{"id":802,"main":"Clouds","description":"scattered clouds","icon":"03n"}],"clouds":{"all":32},"wind":{"speed":2.44,"deg":206,"gust":3.96},"visibility":10000,"pop":0,"sys":{"pod":"n"},"dt_txt":"2025-01-14 06:00:00"},{"dt":1736845200,"main":{"temp":-1.14,"feels_like":-3.84,"temp_min":-1.14,"temp_max":-1.14,"pressure":1036,"sea_level":1036,"grnd_level":999,"humidity":62,"temp_kf":0},"weather":[{"id":804,"main":"Clouds","description":"overcast clouds","icon":"04d"}],"clouds":{"all":92},"wind":{"speed":2.04,"deg":233,"gust":5.46},"visibility":10000,"pop":0,"sys":{"pod":"d"},"dt_txt":"2025-01-14 09:00:00"},{"dt":1736856000,"main":{"temp":1.14,"feels_like":-1.25,"temp_min":1.14,"temp_max":1.14,"pressure":1034,"sea_level":1034,"grnd_level":998,"humidity":57,"temp_kf":0},"weather":[{"id":804,"main":"Clouds","description":"overcast clouds","icon":"04d"}],"clouds":{"all":96},"wind":{"speed":2.1,"deg":250,"gust":6.1},"visibility":10000,"pop":0,"sys":{"pod":"d"},"dt_txt":"2025-01-14 12:00:00"}],"city":{"id":3067696,"name":"Prague","coord":{"lat":50.088,"lon":14.4208},"country":"CZ","population":1165581,"timezone":3600,"sunrise":1736405936,"sunset":1736435971}}